transformer_lite/__init__.py
transformer_lite/core.py
transformer_lite-0.1.1.dist-info/LICENSE
transformer_lite-0.1.1.dist-info/METADATA
transformer_lite-0.1.1.dist-info/WHEEL
transformer_lite-0.1.1.dist-info/top_level.txt
transformer_lite-0.1.1.dist-info/RECORD
