Metadata-Version: 2.1
Name: transformer-lite
Version: 0.1.1
Summary: A tiny library to do basic data transformations
Home-page: https://github.com/drooltu/transformer-lite
Author: Justinas Karaliunas
Author-email: justinas@lorjus.com
License: MIT
Classifier: Development Status :: 3 - Alpha
Classifier: License :: OSI Approved :: MIT License
Classifier: Programming Language :: Python :: 3
Classifier: Programming Language :: Python :: 3.6
Classifier: Programming Language :: Python :: 3.7
Classifier: Programming Language :: Python :: 3.8
Classifier: Programming Language :: Python :: 3.9
Requires-Python: >=3.6
License-File: LICENSE
Requires-Dist: numpy
Provides-Extra: dev
Requires-Dist: pytest ; extra == 'dev'
